{
 "202602010501": {
  "order": [
   [
    1,
    "○",
    15,
    "スイープセレニティ",
    8,
    "岩田望来",
    2,
    "1:09.2"
   ],
   [
    2,
    "△",
    10,
    "ニシノオールワン",
    5,
    "武豊",
    4,
    "1/2馬身"
   ],
   [
    3,
    "▲",
    2,
    "アルサック",
    1,
    "丹内祐次",
    1,
    "クビ"
   ],
   [
    4,
    "・",
    8,
    "スノーガーネット",
    4,
    "横山琉人",
    8,
    "2.1/2馬身"
   ],
   [
    5,
    "☆",
    6,
    "リネアベルタ",
    3,
    "岩田康誠",
    5,
    "ハナ"
   ]
  ],
  "time": "1:09.2",
  "cond": "重",
  "tenki": "晴",
  "pay": [
   [
    "単勝",
    "15",
    "500円"
   ],
   [
    "複勝",
    "15 10 2",
    "140円 / 190円 / 120円"
   ],
   [
    "枠連",
    "5-8",
    "850円"
   ],
   [
    "馬連",
    "10-15",
    "1740円"
   ],
   [
    "ワイド",
    "10 15 2 15 2 10",
    "590円 / 300円 / 410円"
   ],
   [
    "馬単",
    "15-10",
    "3270円"
   ],
   [
    "3連複",
    "2-10-15",
    "1330円"
   ],
   [
    "3連単",
    "15-10-2",
    "8720円"
   ]
  ],
  "check": [
   [
    "◎",
    "14着",
    "miss"
   ],
   [
    "○",
    "1着",
    "hit"
   ],
   [
    "▲",
    "3着",
    "hit"
   ],
   [
    "☆",
    "5着",
    "miss"
   ],
   [
    "☆",
    "10着",
    "miss"
   ],
   [
    "△",
    "2着",
    "hit"
   ],
   [
    "△",
    "6着",
    "miss"
   ]
  ],
  "buycheck": [
   [
    "馬単 ⑯→⑮・②",
    "miss"
   ],
   [
    "3連複本線 ⑯-⑮-②",
    "miss"
   ],
   [
    "3連複 ⑯-⑮②-⑩⑭ 流し",
    "miss"
   ],
   [
    "ミスターX軸 ⑭（アリアス）→3着内",
    "miss"
   ]
  ],
  "fld": {
   "1": [
    11,
    9
   ],
   "2": [
    3,
    1
   ],
   "3": [
    7,
    16
   ],
   "4": [
    12,
    10
   ],
   "5": [
    9,
    15
   ],
   "6": [
    5,
    5
   ],
   "7": [
    10,
    7
   ],
   "8": [
    4,
    8
   ],
   "9": [
    8,
    14
   ],
   "10": [
    2,
    4
   ],
   "11": [
    16,
    12
   ],
   "12": [
    15,
    11
   ],
   "13": [
    13,
    13
   ],
   "14": [
    6,
    6
   ],
   "15": [
    1,
    2
   ],
   "16": [
    14,
    3
   ]
  }
 },
 "202610020101": {
  "order": [
   [
    1,
    "◎",
    1,
    "シスキンブルーム",
    1,
    "団野大成",
    1,
    "1:09.0"
   ],
   [
    2,
    "▲",
    2,
    "スマートメモリー",
    2,
    "吉村誠之",
    3,
    "3.1/2馬身"
   ],
   [
    3,
    "☆",
    5,
    "クリコキアナ",
    5,
    "国分恭介",
    2,
    "1馬身"
   ],
   [
    4,
    "△",
    3,
    "ペプチドニンバス",
    3,
    "富田暁",
    6,
    "7馬身"
   ],
   [
    5,
    "○",
    6,
    "ニドヅケキンシ",
    6,
    "今村聖奈",
    5,
    "1.1/2馬身"
   ]
  ],
  "time": "1:09.0",
  "cond": "重",
  "tenki": "曇",
  "pay": [
   [
    "単勝",
    "1",
    "110円"
   ],
   [
    "複勝",
    "1 2",
    "110円 / 170円"
   ],
   [
    "馬連",
    "1-2",
    "290円"
   ],
   [
    "ワイド",
    "1 2 1 5 2 5",
    "130円 / 130円 / 300円"
   ],
   [
    "馬単",
    "1-2",
    "350円"
   ],
   [
    "3連複",
    "1-2-5",
    "330円"
   ],
   [
    "3連単",
    "1-2-5",
    "750円"
   ]
  ],
  "check": [
   [
    "◎",
    "1着",
    "hit"
   ],
   [
    "○",
    "5着",
    "miss"
   ],
   [
    "▲",
    "2着",
    "hit"
   ],
   [
    "☆",
    "3着",
    "hit"
   ],
   [
    "△",
    "4着",
    "miss"
   ],
   [
    "△",
    "6着",
    "miss"
   ]
  ],
  "buycheck": [
   [
    "馬単 ①→⑥・②",
    "hit"
   ],
   [
    "3連複本線 ①-⑥-②",
    "miss"
   ],
   [
    "3連複 ①-⑥②-③④ 流し",
    "miss"
   ],
   [
    "ミスターX軸 ③（ペプチドニンバス）→3着内",
    "miss"
   ]
  ],
  "fld": {
   "1": [
    1,
    1
   ],
   "2": [
    2,
    3
   ],
   "3": [
    4,
    6
   ],
   "4": [
    6,
    4
   ],
   "5": [
    3,
    2
   ],
   "6": [
    5,
    5
   ]
  }
 }
}